aiogcd/__init__.py
aiogcd/connector/__init__.py
aiogcd/connector/buffer.py
aiogcd/connector/client_token.py
aiogcd/connector/connector.py
aiogcd/connector/decoder.py
aiogcd/connector/entity.py
aiogcd/connector/key.py
aiogcd/connector/path.py
aiogcd/connector/pathelement.py
aiogcd/connector/service_account_token.py
aiogcd/connector/timestampvalue.py
aiogcd/connector/utils.py
aiogcd/orm/__init__.py
aiogcd/orm/filter.py
aiogcd/orm/model.py
aiogcd/orm/utils.py
aiogcd/orm/properties/__init__.py
aiogcd/orm/properties/anyvalue.py
aiogcd/orm/properties/arrayvalue.py
aiogcd/orm/properties/booleanvalue.py
aiogcd/orm/properties/datetimevalue.py
aiogcd/orm/properties/doublevalue.py
aiogcd/orm/properties/integervalue.py
aiogcd/orm/properties/jsonvalue.py
aiogcd/orm/properties/keyvalue.py
aiogcd/orm/properties/stringvalue.py
aiogcd/orm/properties/value.py
aiogcd-0.11.0.dist-info/LICENSE
aiogcd-0.11.0.dist-info/METADATA
aiogcd-0.11.0.dist-info/WHEEL
aiogcd-0.11.0.dist-info/top_level.txt
aiogcd-0.11.0.dist-info/RECORD
