Metadata-Version: 2.1
Name: aiogcd
Version: 0.11.0
Summary: Async Google Cloud Datastore API
Home-page: https://github.com/transceptor-technology/aiogcd
Author: Jeroen van der Heijden
Author-email: jeroen@transceptor.technology
License: UNKNOWN
Download-URL: https://github.com/transceptor-technology/aiogcd/tarball/0.11.0
Keywords: gcd,datastore,connector
Platform: UNKNOWN
Classifier: Development Status :: 4 - Beta
Classifier: Environment :: Other Environment
Classifier: Intended Audience :: Developers
Classifier: License :: OSI Approved :: MIT License
Classifier: Operating System :: OS Independent
Classifier: Programming Language :: Python :: 3
Classifier: Topic :: Software Development
Requires-Dist: aiohttp (>=2)
Requires-Dist: PyJWT (>=1)
Requires-Dist: cryptography (>=1)
Requires-Dist: asyncio-extras (>=1)
